gitbuilding_qaqc_server/__init__.py
gitbuilding_qaqc_server/app.py
gitbuilding_qaqc_server/cli.py
gitbuilding_qaqc_server/qaqc_db.py
gitbuilding_qaqc_server/utilities.py
gitbuilding_qaqc_server/static/GitBuilding500x.png
gitbuilding_qaqc_server/static/favicon-16x16.png
gitbuilding_qaqc_server/static/favicon-32x32.png
gitbuilding_qaqc_server/static/favicon.ico
gitbuilding_qaqc_server/static/css/style.css
gitbuilding_qaqc_server/templates/index.html.jinja
gitbuilding_qaqc_server/templates/report.html.jinja
gitbuilding_qaqc_server-0.0.1.dist-info/METADATA
gitbuilding_qaqc_server-0.0.1.dist-info/WHEEL
gitbuilding_qaqc_server-0.0.1.dist-info/entry_points.txt
gitbuilding_qaqc_server-0.0.1.dist-info/licenses/LICENSE
gitbuilding_qaqc_server-0.0.1.dist-info/RECORD
