Metadata-Version: 2.4
Name: gitbuilding_qaqc_server
Version: 0.0.1
Summary: An experimental server for storing QA/QC data.
Author-email: Julian Stirling <julian@julianstirling.co.uk>
License-Expression: AGPL-3.0-or-later
License-File: LICENSE
Keywords: Documentation,Hardware
Requires-Python: >=3.11
Requires-Dist: aiosqlite~=0.21.0
Requires-Dist: fastapi[all]~=0.116
Provides-Extra: dev
Requires-Dist: codespell~=2.4; extra == 'dev'
Requires-Dist: curlylint; extra == 'dev'
Requires-Dist: hypothesis~=6.138; extra == 'dev'
Requires-Dist: lxml~=6.0; extra == 'dev'
Requires-Dist: mypy-gitlab-code-quality~=1.3; extra == 'dev'
Requires-Dist: mypy~=1.17; extra == 'dev'
Requires-Dist: pytest-asyncio~=1.1; extra == 'dev'
Requires-Dist: pytest-cov~=6.2; extra == 'dev'
Requires-Dist: pytest-mock~=3.14; extra == 'dev'
Requires-Dist: pytest~=8.4; extra == 'dev'
Requires-Dist: ruff~=0.12; extra == 'dev'
